FoBiS.py-3.0.5.data/scripts/FoBiS.py
fobis/Builder.py
fobis/Cleaner.py
fobis/Colors.py
fobis/Compiler.py
fobis/Dependency.py
fobis/Doctest.py
fobis/FoBiSConfig.py
fobis/Fobos.py
fobis/Gcov.py
fobis/ParsedFile.py
fobis/__init__.py
fobis/cli_parser.py
fobis/fobis.py
fobis/utils.py
FoBiS.py-3.0.5.dist-info/LICENSE.gpl3.md
FoBiS.py-3.0.5.dist-info/METADATA
FoBiS.py-3.0.5.dist-info/WHEEL
FoBiS.py-3.0.5.dist-info/entry_points.txt
FoBiS.py-3.0.5.dist-info/top_level.txt
FoBiS.py-3.0.5.dist-info/RECORD
