Metadata-Version: 2.1
Name: FoBiS.py
Version: 3.0.5
Summary: a Fortran Building System for poor men
Home-page: https://github.com/szaghi/FoBiS
Author: Stefano Zaghi
Author-email: stefano.zaghi@gmail.com
License: UNKNOWN
Platform: UNKNOWN
Classifier: Development Status :: 5 - Production/Stable
Classifier: License :: OSI Approved :: GNU General Public License v3 (GPLv3)
Classifier: Environment :: Console
Classifier: Intended Audience :: End Users/Desktop
Classifier: Programming Language :: Python
Classifier: Programming Language :: Python :: 2
Classifier: Programming Language :: Python :: 2.7
Classifier: Programming Language :: Python :: 3
Classifier: Programming Language :: Python :: 3.8
Classifier: Topic :: Text Processing
Requires-Dist: configparser
Requires-Dist: future
Provides-Extra: ford
Requires-Dist: FORD (>=1.1.0) ; extra == 'ford'
Provides-Extra: preform.py
Requires-Dist: PreForM.py (>=v1.1.1) ; extra == 'preform.py'
Provides-Extra: graphviz
Requires-Dist: graphviz (>=0.4.2) ; extra == 'graphviz'
